build_settings/__init__.py
build_settings/normal_use_test.py
build_settings/settings.py
build_settings/tests.py
build_settings-0.1.7.dist-info/LICENSE
build_settings-0.1.7.dist-info/METADATA
build_settings-0.1.7.dist-info/WHEEL
build_settings-0.1.7.dist-info/top_level.txt
build_settings-0.1.7.dist-info/RECORD
