Metadata-Version: 2.1
Name: build-settings
Version: 0.1.7
Summary: An extension of configparser
Home-page: https://github.com/manbehindthemadness/build-settings
Author: Manbehindthemadness
Author-email: manbehindthemadness@gmail.com
Classifier: Programming Language :: Python :: 3
Classifier: License :: OSI Approved :: MIT License
Classifier: Operating System :: OS Independent
Requires-Python: >=3.6
License-File: LICENSE
Requires-Dist: psutil
Provides-Extra: testing
Requires-Dist: unittest-mock ; extra == 'testing'
